tabular_toolbox/__init__.py
tabular_toolbox/column_selector.py
tabular_toolbox/const.py
tabular_toolbox/dask_ex.py
tabular_toolbox/data_cleaner.py
tabular_toolbox/dataframe_mapper.py
tabular_toolbox/drift_detection.py
tabular_toolbox/feature_selection.py
tabular_toolbox/metrics.py
tabular_toolbox/persistence.py
tabular_toolbox/sklearn_ex.py
tabular_toolbox/datasets/Bike_Sharing.csv
tabular_toolbox/datasets/__init__.py
tabular_toolbox/datasets/bank-uci.csv.gz
tabular_toolbox/datasets/blood.csv
tabular_toolbox/datasets/dsutils.py
tabular_toolbox/datasets/glass_uci.csv
tabular_toolbox/datasets/telescope.csv
tabular_toolbox/ensemble/__init__.py
tabular_toolbox/ensemble/base_ensemble.py
tabular_toolbox/ensemble/dask_ensemble.py
tabular_toolbox/ensemble/stacking.py
tabular_toolbox/ensemble/voting.py
tabular_toolbox/evaluator/__init__.py
tabular_toolbox/evaluator/_base.py
tabular_toolbox/evaluator/auto_sklearn.py
tabular_toolbox/evaluator/h2o.py
tabular_toolbox/evaluator/hyperdt.py
tabular_toolbox/evaluator/hypergbm.py
tabular_toolbox/evaluator/tests.py
tabular_toolbox/examples/__init__.py
tabular_toolbox/tests/__init__.py
tabular_toolbox/tests/column_selector_test.py
tabular_toolbox/tests/dask_ex_test.py
tabular_toolbox/tests/data_cleaner_test.py
tabular_toolbox/tests/drift_detection_test.py
tabular_toolbox/tests/sklearn_transformer_test.py
tabular_toolbox/tests/utils_test.py
tabular_toolbox/tests/ensemble/__init__.py
tabular_toolbox/tests/ensemble/ensemble_test.py
tabular_toolbox/utils/__init__.py
tabular_toolbox/utils/_common.py
tabular_toolbox/utils/logging.py
tabular_toolbox-0.1.4.dist-info/LICENSE
tabular_toolbox-0.1.4.dist-info/METADATA
tabular_toolbox-0.1.4.dist-info/WHEEL
tabular_toolbox-0.1.4.dist-info/top_level.txt
tabular_toolbox-0.1.4.dist-info/RECORD
